MANIFEST.in
README.md
requirements.txt
setup.py
sport_tracker/__init__.py
sport_tracker/__main__.py
sport_tracker/argparser.py
sport_tracker/logger.py
sport_tracker.egg-info/PKG-INFO
sport_tracker.egg-info/SOURCES.txt
sport_tracker.egg-info/dependency_links.txt
sport_tracker.egg-info/entry_points.txt
sport_tracker.egg-info/requires.txt
sport_tracker.egg-info/top_level.txt
sport_tracker/common/__init__.py
sport_tracker/common/exceptions.py
sport_tracker/controller/activity_actions.py
sport_tracker/controller/argument_actions.py
sport_tracker/controller/db_controller.py
sport_tracker/controller/sport_actions.py
sport_tracker/controller/user_actions.py
sport_tracker/view/__init__.py
sport_tracker/view/graphical_output.py
sport_tracker/view/terminal_output.py